ovos_solver_failure_plugin/__init__.py
ovos_solver_failure_plugin/version.py
ovos_solver_failure_plugin-0.0.3.dist-info/licenses/LICENSE
ovos_solver_failure_plugin-0.0.3.dist-info/METADATA
ovos_solver_failure_plugin-0.0.3.dist-info/WHEEL
ovos_solver_failure_plugin-0.0.3.dist-info/entry_points.txt
ovos_solver_failure_plugin-0.0.3.dist-info/top_level.txt
ovos_solver_failure_plugin-0.0.3.dist-info/zip-safe
ovos_solver_failure_plugin-0.0.3.dist-info/RECORD
