Metadata-Version: 2.4
Name: ovos_solver_failure_plugin
Version: 0.0.3
Summary: A question solver plugin for ovos/neon/mycroft
Home-page: https://github.com/OpenVoiceOS/ovos-solver-failure-plugin
Author: jarbasai
Author-email: jarbasai@mailfence.com
License: MIT
Keywords: mycroft plugin utterance fallback query
License-File: LICENSE
Requires-Dist: ovos-plugin-manager<3.0.0,>=0.0.26
Dynamic: author
Dynamic: author-email
Dynamic: description
Dynamic: description-content-type
Dynamic: home-page
Dynamic: keywords
Dynamic: license
Dynamic: license-file
Dynamic: requires-dist
Dynamic: summary
